sv-uvm/system-verilog/inverter/inverter.sv
# verilator --binary --trace -j 1 -Wall inverter.sv 
module inverter;

logic clk=0;
//logic d=0;
logic q=0;

always #1 clk <= ~clk;

always_ff @(posedge clk)
begin
    q <= ~q;
end

initial begin
    #20 $finish; // 47 units of time till now

end
initial begin
    $dumpfile("sim_dump.vcd"); // Name of the output file
    $dumpvars(0, inverter);
end
always @(posedge clk)
    $display("[%0t] q=%0b",$time,q);

endmodule

sv-uvm/system-verilog/inverter/sim_dump.vcd
$version Generated by VerilatedVcd $end
$timescale 1ps $end
 $scope module $rootio $end
 $upscope $end
 $scope module inverter $end
  $var wire 1 # clk $end
  $var wire 1 $ q $end
 $upscope $end
$enddefinitions $end


#0
0#
0$
#1
1#
1$
#2
0#
#3
1#
0$
#4
0#
#5
1#
1$
#6
0#
#7
1#
0$
#8
0#
#9
1#
1$
#10
0#
#11
1#
0$
#12
0#
#13
1#
1$
#14
0#
#15
1#
0$
#16
0#
#17
1#
1$
#18
0#
#19
1#
0$
